ometria/__init__.py
ometria/ometria.py
ometria-1.0.0.dist-info/AUTHORS.rst
ometria-1.0.0.dist-info/LICENSE
ometria-1.0.0.dist-info/METADATA
ometria-1.0.0.dist-info/WHEEL
ometria-1.0.0.dist-info/top_level.txt
ometria-1.0.0.dist-info/RECORD
