Metadata-Version: 2.1
Name: ometria
Version: 1.0.0
Summary: Python wrapper for the Ometria API
Home-page: https://github.com/nwjlyons/ometria
Author: Neil Lyons
Author-email: nwjlyons@googlemail.com
License: BSD
Keywords: ometria
Platform: UNKNOWN
Classifier: Development Status :: 5 - Production/Stable
Classifier: Intended Audience :: Developers
Classifier: License :: OSI Approved :: BSD License
Classifier: Natural Language :: English
Classifier: Programming Language :: Python :: 3
Classifier: Programming Language :: Python :: 3.5
Classifier: Programming Language :: Python :: 3.6
Requires-Dist: requests
